MANIFEST.in
README.md
kangrouter.py
setup.py
kangrouter_py.egg-info/PKG-INFO
kangrouter_py.egg-info/SOURCES.txt
kangrouter_py.egg-info/dependency_links.txt
kangrouter_py.egg-info/requires.txt
kangrouter_py.egg-info/top_level.txt
test/test.py
tsm/__init__.py
tsm/common/__init__.py
tsm/common/app/__init__.py
tsm/common/app/exception.py