Metadata-Version: 1.1
Name: kangrouter-py
Version: 1.0.4
Summary: Python client for the KangRouter transportation service optimizer.
Home-page: https://github.com/TheSolvingMachine/kangrouter-py
Author: TheSolvingMachine
Author-email: support@thesolvingmachine.com
License: Apache
Download-URL: https://github.com/TheSolvingMachine/kangrouter-py/tarball/1.0.4
Keywords: Vehicle Routing With Time Windows,Pickup and Delivery,Optimization
Platform: UNKNOWN
Classifier: Development Status :: 3 - Alpha
Classifier: Intended Audience :: Developers
Classifier: License :: OSI Approved :: Apache Software License
Classifier: Topic :: Scientific/Engineering :: Artificial Intelligence
Classifier: Programming Language :: Python :: 2
Classifier: Programming Language :: Python :: 3
